{
  "type": "Feature",
  "stac_version": "1.0.0",
  "id": "MYD10A1.A2022043.h21v04.061",
  "properties": {
    "start_datetime": "2022-02-12T00:00:00Z",
    "end_datetime": "2022-02-12T23:59:59Z",
    "instruments": [
      "modis"
    ],
    "platform": "aqua",
    "created": "2022-02-14T03:57:02Z",
    "updated": "2022-02-13T21:01:32.595000Z",
    "modis:horizontal-tile": 21,
    "modis:vertical-tile": 4,
    "modis:tile-id": "51021004",
    "proj:epsg": null,
    "proj:wkt2": "PROJCRS[\"unnamed\",BASEGEOGCRS[\"Unknown datum based upon the custom spheroid\",DATUM[\"Not specified (based on custom spheroid)\",ELLIPSOID[\"Custom spheroid\",6371007.181,0,LENGTHUNIT[\"metre\",1,ID[\"EPSG\",9001]]]],PRIMEM[\"Greenwich\",0,ANGLEUNIT[\"degree\",0.0174532925199433,ID[\"EPSG\",9122]]]],CONVERSION[\"unnamed\",METHOD[\"Sinusoidal\"],PARAMETER[\"Longitude of natural origin\",0,ANGLEUNIT[\"degree\",0.0174532925199433],ID[\"EPSG\",8802]],PARAMETER[\"False easting\",0,LENGTHUNIT[\"metre\",1],ID[\"EPSG\",8806]],PARAMETER[\"False northing\",0,LENGTHUNIT[\"metre\",1],ID[\"EPSG\",8807]]],CS[Cartesian,2],AXIS[\"easting\",east,ORDER[1],LENGTHUNIT[\"metre\",1,ID[\"EPSG\",9001]]],AXIS[\"northing\",north,ORDER[2],LENGTHUNIT[\"metre\",1,ID[\"EPSG\",9001]]]]",
    "proj:geometry": {
      "type": "Polygon",
      "coordinates": [
        [
          [
            4447802.078667,
            4447802.078667
          ],
          [
            4447802.078667,
            5559752.598333
          ],
          [
            3335851.559,
            5559752.598333
          ],
          [
            3335851.559,
            4447802.078667
          ],
          [
            4447802.078667,
            4447802.078667
          ]
        ]
      ]
    },
    "proj:shape": [
      2400,
      2400
    ],
    "proj:transform": [
      463.3127165279167,
      0.0,
      3335851.559,
      0.0,
      -463.31271652750013,
      5559752.598333
    ],
    "eo:cloud_cover": 61,
    "datetime": null
  },
  "geometry": {
    "type": "Polygon",
    "coordinates": [
      [
        [
          46.67280666510629,
          49.997938261833234
        ],
        [
          46.135294765126936,
          49.435438524766404
        ],
        [
          45.60677278061754,
          48.864605458261536
        ],
        [
          45.08729030774586,
          48.285439062318645
        ],
        [
          44.576886749625146,
          47.69793933693773
        ],
        [
          44.07559205084347,
          47.10210628211878
        ],
        [
          43.58342740656583,
          46.49793989786182
        ],
        [
          43.100405946135815,
          45.88544018416682
        ],
        [
          42.62966238644216,
          45.2687738057528
        ],
        [
          42.16786464548319,
          44.64377409790077
        ],
        [
          41.71208325542618,
          44.00627439589169
        ],
        [
          41.265434954873854,
          43.360441364444576
        ],
        [
          40.82790178015836,
          42.70627500355944
        ],
        [
          40.399461282754245,
          42.04377531323628
        ],
        [
          39.980087044277546,
          41.37294229347509
        ],
        [
          39.56974916993539,
          40.69377594427588
        ],
        [
          39.1660243824297,
          40.002109600919624
        ],
        [
          52.215055140742045,
          40.002109600919624
        ],
        [
          52.75328980646806,
          40.69377594427588
        ],
        [
          53.30034085576277,
          41.37294229347509
        ],
        [
          53.85943893456831,
          42.04377531323628
        ],
        [
          54.43062389779167,
          42.70627500355944
        ],
        [
          55.01393096568806,
          43.360441364444576
        ],
        [
          55.609390066007684,
          44.00627439589169
        ],
        [
          56.217025147413274,
          44.64377409790077
        ],
        [
          56.832681060625134,
          45.2687738057528
        ],
        [
          57.46026329073732,
          45.88544018416682
        ],
        [
          58.10421407686381,
          46.49793989786182
        ],
        [
          58.760354301573706,
          47.10210628211878
        ],
        [
          59.428666461191035,
          47.69793933693773
        ],
        [
          60.10912229891094,
          48.285439062318645
        ],
        [
          60.801681893440836,
          48.864605458261536
        ],
        [
          61.506292713645315,
          49.435438524766404
        ],
        [
          62.222888639291995,
          49.997938261833234
        ],
        [
          46.67280666510629,
          49.997938261833234
        ]
      ]
    ]
  },
  "links": [
    {
      "rel": "root",
      "href": "../../../catalog.json",
      "type": "application/json",
      "title": "MODIS"
    },
    {
      "rel": "collection",
      "href": "../collection.json",
      "type": "application/json",
      "title": "MODIS Snow Cover Daily"
    },
    {
      "rel": "parent",
      "href": "../collection.json",
      "type": "application/json",
      "title": "MODIS Snow Cover Daily"
    }
  ],
  "assets": {
    "NDSI": {
      "href": "../../../../tests/data-files/external/MYD10A1.A2022043.h21v04.061.2022045035657_NDSI.tif",
      "type": "image/tiff; application=geotiff; profile=cloud-optimized",
      "title": "Raw NDSI values (i.e. prior to screening).",
      "raster:bands": [
        {
          "data_type": "int16",
          "spatial_resolution": 500,
          "scale": 0.0001
        }
      ],
      "roles": [
        "data"
      ]
    },
    "NDSI_Snow_Cover": {
      "href": "../../../../tests/data-files/external/MYD10A1.A2022043.h21v04.061.2022045035657_NDSI_Snow_Cover.tif",
      "type": "image/tiff; application=geotiff; profile=cloud-optimized",
      "title": "Gridded NDSI snow cover and data flag values.",
      "raster:bands": [
        {
          "data_type": "uint8",
          "spatial_resolution": 500
        }
      ],
      "eo:cloud_cover": 61,
      "roles": [
        "data"
      ]
    },
    "NDSI_Snow_Cover_Algorithm_Flags_QA": {
      "href": "../../../../tests/data-files/external/MYD10A1.A2022043.h21v04.061.2022045035657_NDSI_Snow_Cover_Algorithm_Flags_QA.tif",
      "type": "image/tiff; application=geotiff; profile=cloud-optimized",
      "title": "Algorithm-specific bit flags set for data screens and for inland water.",
      "raster:bands": [
        {
          "data_type": "uint8",
          "spatial_resolution": 500
        }
      ],
      "roles": [
        "data"
      ]
    },
    "NDSI_Snow_Cover_Basic_QA": {
      "href": "../../../../tests/data-files/external/MYD10A1.A2022043.h21v04.061.2022045035657_NDSI_Snow_Cover_Basic_QA.tif",
      "type": "image/tiff; application=geotiff; profile=cloud-optimized",
      "title": "A general estimate of the quality of the algorithm result.",
      "raster:bands": [
        {
          "data_type": "uint8",
          "spatial_resolution": 500
        }
      ],
      "classification:classes": [
        {
          "value": 0,
          "description": "best"
        },
        {
          "value": 1,
          "description": "good"
        },
        {
          "value": 2,
          "description": "ok"
        },
        {
          "value": 3,
          "description": "poor (not used)"
        },
        {
          "value": 4,
          "description": "other (not used)"
        }
      ],
      "roles": [
        "data"
      ]
    },
    "Snow_Albedo_Daily_Tile": {
      "href": "../../../../tests/data-files/external/MYD10A1.A2022043.h21v04.061.2022045035657_Snow_Albedo_Daily_Tile.tif",
      "type": "image/tiff; application=geotiff; profile=cloud-optimized",
      "title": "Daily snow albedo corresponding to the NDSI_Snow_Cover parameter.",
      "raster:bands": [
        {
          "data_type": "uint8",
          "spatial_resolution": 500
        }
      ],
      "eo:cloud_cover": 61,
      "roles": [
        "data"
      ]
    },
    "granule_pnt": {
      "href": "../../../../tests/data-files/external/MYD10A1.A2022043.h21v04.061.2022045035657_granule_pnt.tif",
      "type": "image/tiff; application=geotiff; profile=cloud-optimized",
      "title": "Pointer for identifying the swath mapped into each grid cell.",
      "raster:bands": [
        {
          "data_type": "uint8",
          "spatial_resolution": 500
        }
      ],
      "roles": [
        "data"
      ]
    },
    "hdf": {
      "href": "../../../../tests/data-files/external/MYD10A1.A2022043.h21v04.061.2022045035657.hdf",
      "type": "application/x-hdf",
      "title": "Source data containing all bands",
      "roles": [
        "data"
      ]
    },
    "metadata": {
      "href": "../../../../tests/data-files/external/MYD10A1.A2022043.h21v04.061.2022045035657.hdf.xml",
      "type": "application/xml",
      "title": "Federal Geographic Data Committee (FGDC) Metadata",
      "roles": [
        "metadata"
      ]
    },
    "orbit_pnt": {
      "href": "../../../../tests/data-files/external/MYD10A1.A2022043.h21v04.061.2022045035657_orbit_pnt.tif",
      "type": "image/tiff; application=geotiff; profile=cloud-optimized",
      "title": "Pointer to the orbit of the swath mapped into each grid cell.",
      "raster:bands": [
        {
          "data_type": "uint8",
          "spatial_resolution": 500
        }
      ],
      "roles": [
        "data"
      ]
    }
  },
  "bbox": [
    39.1660243824297,
    40.002109600919624,
    62.222888639291995,
    49.997938261833234
  ],
  "stac_extensions": [
    "https://stac-extensions.github.io/projection/v1.0.0/schema.json",
    "https://stac-extensions.github.io/eo/v1.0.0/schema.json",
    "https://stac-extensions.github.io/raster/v1.1.0/schema.json",
    "https://stac-extensions.github.io/classification/v1.0.0/schema.json"
  ],
  "collection": "modis-10A1-061"
}